vietnamese_poem_classifier/__init__.py
vietnamese_poem_classifier/poem_classifier.py
vietnamese_poem_classifier/rhymes.txt
vietnamese_poem_classifier/start_vowels.txt
vietnamese_poem_classifier-0.1.6.dist-info/LICENSE
vietnamese_poem_classifier-0.1.6.dist-info/METADATA
vietnamese_poem_classifier-0.1.6.dist-info/WHEEL
vietnamese_poem_classifier-0.1.6.dist-info/entry_points.txt
vietnamese_poem_classifier-0.1.6.dist-info/top_level.txt
vietnamese_poem_classifier-0.1.6.dist-info/RECORD
